matridge/__init__.py
matridge/__main__.py
matridge/command.py
matridge/config.py
matridge/contact.py
matridge/gateway.py
matridge/group.py
matridge/matrix.py
matridge/reactions.py
matridge/session.py
matridge/util.py
matridge-0.3.1.dist-info/licenses/LICENSE
matridge-0.3.1.dist-info/METADATA
matridge-0.3.1.dist-info/WHEEL
matridge-0.3.1.dist-info/entry_points.txt
matridge-0.3.1.dist-info/top_level.txt
matridge-0.3.1.dist-info/RECORD
