Metadata-Version: 2.4
Name: matridge
Version: 0.3.1
Summary: A Matrix/XMPP gateway
Author-email: Nicolas Cedilnik <nicoco@nicoco.fr>
License-Expression: AGPL-3.0-or-later
Project-URL: Homepage, https://codeberg.org/slidge/matridge
Project-URL: Issues, https://codeberg.org/slidge/matridge/issues
Project-URL: Repository, https://codeberg.org/slidge/matridge
Project-URL: Chat room, https://slidge.im/xmpp-web/#/guest?join=slidge@conference.nicoco.fr
Project-URL: Documentation, https://slidge.im/docs/matridge/main
Project-URL: changelog, https://codeberg.org/slidge/matridge/releases
Keywords: xmpp,gateway,bridge,instant messaging,chat,matrix
Classifier: Topic :: Internet :: XMPP
Requires-Python: >=3.11
License-File: LICENSE
Requires-Dist: matrix-nio[e2e]<0.26,>=0.25
Requires-Dist: beautifulsoup4<5,>=4.12.2
Requires-Dist: async-lru<3,>=2.0.3
Requires-Dist: slidge-style-parser>=0.1.6
Requires-Dist: slidge<0.4,>=0.3.0alpha3
Dynamic: license-file
